ffit/__config__.py
ffit/__init__.py
ffit/config.py
ffit/fit_logic.py
ffit/fit_results.py
ffit/fit_utils.py
ffit/front.py
ffit/stats.py
ffit/utils.py
ffit/backends/__init__.py
ffit/backends/jax_backend.py
ffit/backends/protocol.py
ffit/backends/scipy_backend.py
ffit/funcs/__init__.py
ffit/funcs/complex_spiral.py
ffit/funcs/cos.py
ffit/funcs/exp.py
ffit/funcs/exp_decaying_cos.py
ffit/funcs/gaussian.py
ffit/funcs/hyperbola.py
ffit/funcs/line.py
ffit/funcs/log.py
ffit/funcs/lorentzian.py
ffit/funcs/lorentzian_complex.py
ffit/funcs/parabola.py
ffit/funcs/polynomial.py
ffit/funcs/sinc.py
ffit-1.2.0.dist-info/licenses/LICENCE
ffit-1.2.0.dist-info/METADATA
ffit-1.2.0.dist-info/WHEEL
ffit-1.2.0.dist-info/top_level.txt
ffit-1.2.0.dist-info/RECORD
