Metadata-Version: 2.4
Name: ffit
Version: 1.2.0
Summary: Fit python library
Home-page: https://github.com/kyrylo-gr/ffit
Author: kyrylo.gr
Author-email: git@kyrylo.gr
Classifier: Programming Language :: Python :: 3
Classifier: Operating System :: OS Independent
Requires-Python: >=3.8
License-File: LICENCE
Requires-Dist: numpy
Requires-Dist: scipy
Dynamic: author
Dynamic: author-email
Dynamic: classifier
Dynamic: description
Dynamic: description-content-type
Dynamic: home-page
Dynamic: license-file
Dynamic: requires-dist
Dynamic: requires-python
Dynamic: summary
